nftl_slack_tools/__init__.py
nftl_slack_tools/client.py
nftl_slack_tools/slack_api.py
nftl_slack_tools/api/__init__.py
nftl_slack_tools/api/channels.py
nftl_slack_tools/api/chat.py
nftl_slack_tools/api/groups.py
nftl_slack_tools/api/signup.py
nftl_slack_tools/api/users.py
nftl_slack_tools-0.3.0.dist-info/METADATA
nftl_slack_tools-0.3.0.dist-info/RECORD
nftl_slack_tools-0.3.0.dist-info/WHEEL
nftl_slack_tools-0.3.0.dist-info/top_level.txt
nftl_slack_tools-0.3.0.dist-info/zip-safe
tests/__init__.py
tests/slack_client_groups_test.py
tests/slack_client_signup_test.py
tests/slack_client_test.py
