Metadata-Version: 2.1
Name: nftl-slack-tools
Version: 0.3.0
Summary: Tool 4 partial Slack API handling
Home-page: UNKNOWN
Author: Grzegorz Pawełczuk
Author-email: grzegorz.pawelczuk@nftlearning.com
License: UNKNOWN
Platform: UNKNOWN
Classifier: Programming Language :: Python :: 3
Classifier: License :: OSI Approved :: MIT License
Classifier: Operating System :: OS Independent
Requires-Dist: requests (>=2.9.11)
Requires-Dist: typing (>=3.5.3.0)
Requires-Dist: responses (>=0.9.0)
